mailqueue/__init__.py
mailqueue/admin.py
mailqueue/apps.py
mailqueue/defaults.py
mailqueue/models.py
mailqueue/receivers.py
mailqueue/tasks.py
mailqueue/urls.py
mailqueue/utils.py
mailqueue/views.py
mailqueue/management/__init__.py
mailqueue/management/commands/__init__.py
mailqueue/management/commands/clear_sent_messages.py
mailqueue/management/commands/send_queued_messages.py
mailqueue/migrations/0001_initial.py
mailqueue/migrations/0002_mailermessage_reply_to.py
mailqueue/migrations/0003_auto_20160920_1458.py
mailqueue/migrations/0004_mailermessage_created.py
mailqueue/migrations/0005_cc_address_created.py
mailqueue/migrations/0006_auto_20190815_1926.py
mailqueue/migrations/0007_auto_20200318_0651.py
mailqueue/migrations/0008_alter_attachment_file_attachment_and_more.py
mailqueue/migrations/__init__.py
mailqueue/tests/__init__.py
mailqueue/tests/factories.py
mailqueue/tests/test_messages.py
mailqueue/tests/test_smoke.py
mailqueue/tests/utils.py
django_mail_queue-3.2.6.dist-info/AUTHORS
django_mail_queue-3.2.6.dist-info/LICENSE
django_mail_queue-3.2.6.dist-info/METADATA
django_mail_queue-3.2.6.dist-info/WHEEL
django_mail_queue-3.2.6.dist-info/top_level.txt
django_mail_queue-3.2.6.dist-info/RECORD
